fortran77punchcards/__init__.py
fortran77punchcards/__main__.py
fortran77punchcards/character_encoding.py
fortran77punchcards/punch.py
fortran77punchcards/punchcard.png
fortran77punchcards/py.typed
fortran77punchcards-0.0.1.dist-info/LICENSE
fortran77punchcards-0.0.1.dist-info/LICENSE-CC
fortran77punchcards-0.0.1.dist-info/METADATA
fortran77punchcards-0.0.1.dist-info/WHEEL
fortran77punchcards-0.0.1.dist-info/RECORD
