Metadata-Version: 2.3
Name: fortran77punchcards
Version: 0.0.1
Summary: convert FORTRAN77 code to images of punchcards
License: MIT (all files except fortran77punchcards/punchcard.png)
Author: Matthew Scroggs
Author-email: fortran@mscroggs.co.uk
Requires-Python: >=3.8.0
Classifier: License :: Other/Proprietary License
Classifier: Programming Language :: Python :: 3
Classifier: Programming Language :: Python :: 3.8
Classifier: Programming Language :: Python :: 3.9
Classifier: Programming Language :: Python :: 3.10
Classifier: Programming Language :: Python :: 3.11
Classifier: Programming Language :: Python :: 3.12
Classifier: Programming Language :: Python :: 3.13
Provides-Extra: ci
Provides-Extra: style
Provides-Extra: test
Requires-Dist: Pillow
Requires-Dist: fortran77punchcards[style,test] ; extra == "ci"
Requires-Dist: mypy ; extra == "style"
Requires-Dist: pytest ; extra == "test"
Requires-Dist: ruff ; extra == "style"
Project-URL: Homepage, https://github.com/mscroggs/fortran77punchcards
Project-URL: Repository, https://github.com/mscroggs/fortran77punchcards
